mac_unit.v
// MAC unit for integer (or fixed point in the future) arithmetic

// Infrastructure for future fixed point arithmetic
// `define FIXED_POINT 1
// Verified to be syntatically correct

module mac_unit #(
    parameter M = 16, // DEFAULT Width of integer bits
    parameter Q = 12 // DEFAULT Width of fractional bits
)(
    input clk, rst, clk_en,
    // MAC operation: out = a * b + c
    input [M-1:0] a, // Multiplier
    input [M-1:0] b, // Multiplicand
    input [M-1:0] c, // Accumulator
    // output [M-1:0] out 
    // CHANGE NOTE 1: Changing the output from a wire to a register
    // With this change, we're putting the responsibility of the storage
    // of the output on the user of the module
    // Implication: A register array is definition is required in the
    // outer module to store the output of the MAC unit
    // CHANGE NOTE 2: Changing the output from a register back to a wire
    // We are exporting the calculate value straight to the shift register
    // array element when the calculation is done.
    output [(M-1):0] out // 
    // output [(M-1):0] out // 
);

assign out = a * b + c;

// reg [M-1:0] temp_reg;
// REFER TO CHANGE NOTE 1
// REFER TO CHANGE NOTE 2
// always @(
//     // posedge clk or
//     posedge clk,
//     posedge rst
// ) begin
//     if (rst) begin
//         // If asynchronous reset is on
//         out <= 0; // Reset the register to 0
//         // out = 0; // Reset the register to 0
//         // REFER TO CHANGE NOTE 1
//     end 
//     else if (clk_en) begin
//         // If the async reset is off and the clock is enabled
//         // Normal MAC operation is performed
//         out <= a * b + c;
//         // out = a * b + c;
//         // REFER TO CHANGE NOTE 1
//     end
// end


// Note that temp_reg is directly assigned to out since temp_reg is 
// updated sequentially
// assign out = temp_reg;
// REFER TO CHANGE NOTE 1

// initial begin
//     $display("MAC unit simulation started");
// end
    
endmodule

convolver.v
// Module declaration with inputs and outputs
module convolution #( // Declaring convolution as a parameterized module
    // Parameter list BEGINS
    parameter N = 8'h0a,    // Side length of input matrix
    parameter K = 8'h03,    // Side length of kernel
    parameter S = 1,        // Stride size (horizontal stride = vertical stride)
    parameter WIDTH = 16,   // Width of the bits used
    parameter Q = 12,       // Number of fractional bits in the case of fixed point
    parameter padding = 1   // Use padding or not
    // Parameter list ENDS
)(
    input clk,              // Clock signal
    input clk_en,           // Clock enables
    input glb_rst,          // Global reset signal

    // Notice that the kernel matrix is flattened into a 1D array
    // There are K*K elements in the kernel
    // Each element is of WIDTH bits
    // In total, there are K*K*WIDTH bits in the kernel matrix
    input [(WIDTH-1):0] input_val, // ONE element of the input matrix
    input [(K*K*WIDTH-1):0] kernel_1d, // 1D version of the kernel matrix

    output [WIDTH-1:0] conv_result, // Output of the convolution
    output result_valid, // Output signal to indicate that the result is valid
    output conv_end // End of convolution signal
);

// PART 1: Instatiation Statements STARTS HERE

// Instantiation of kernel_2d: Conversion of Kernel from 1D to 2D
// Note that the structure of the so-called 2D kernel is a
// 1D array of KxK elements, where each element is of 
// [(WIDTH-1):0] wide.
wire [(WIDTH - 1):0] kernel_2d [0:(K * K - 1)];
generate
	genvar n;
    for (n=0; n<(K*K); n=n+1) 
    begin
        // Syntax explanation:
        // Selecting WIDTH bits inclusively, starting from the bit position (WIDTH * l)
        assign kernel_2d[n][WIDTH-1:0] = kernel_1d[(WIDTH * n) +: WIDTH];
    end
endgenerate

// Instantiation of shift_reg vector:
// Size of shift_reg:
// - x1 element to store 0 for all times as the input to the first MAC unit.
//  - Located at the Top left corner of Active Section
// - x((K - 1) * N) elements to act as shift register of the top (K-1)
// rows of the Active Section and the entirety of the Dormant Section 
//  - Constitute the main body of the array
// - xK elements to store the LAST row of the Active Section 
// TOTAL SIZE = 1 + ((K - 1) * N) + K
// So, the range is 0 to ((K - 1) * N) + K inclusive

// Each element of shift_reg is a series of binary of size:
// [(WIDTH-1):0]

reg [WIDTH-1:0] shift_reg [0:(((K - 1) * N) + K)];

// Initialize wires that leads to each of the element within register array
// except the 0-indexed one.
wire [WIDTH-1:0] reg_wire_to [0:(((K - 1) * N) + K)];

reg result_valid_reg;
reg conv_end_reg;

// PART 1: Instatiation Statements ENDS HERE




// PART 2: Spatial traversal for operation definition STARTS HERE

// More specifically, in this part, we go over the entire shift_reg array
// to specify where Active Section and Dormant Section are located, and 
// generate the hardware need to do what should be done in each section.

// Notice that the shift_reg array is inherently a 1D array. This means
// we have to keep track of where we are in the conceptually 2D array.

// Initial Section: The first element of the shift_reg array
// This should contain the value 0 at all times to be used as the input
// to the first MAC unit.
// assign shift_reg[0] = 'd0;

// Register Array Exit Point: The last element of the shift_reg array 
// should be the output of the entire Convolution operation.
                            //    1 + ((K - 1) * N) + K
assign conv_result = shift_reg[((K - 1) * N) + K];


// Convolution Final Exit Point: The current input element is the last
// in the input matrix. The Convolution operation is ending.
assign conv_end = conv_end_reg;

assign result_valid = result_valid_reg;




generate
    genvar k; // Indexing which ROW of the register array we're situated in.
    genvar l; // Indexing which COLUMN of the register array we're situated in.

    for (k=0; k < K; k=k+1) 
    begin // For each row of shift_reg
        
        for (l=0; l < N; l=l+1) 
        begin // For each element of shift_reg
            
            // ACTIVE SECTION OPERATIONS STARTS HERE
            // if ((k >= 0 && k <= (Convolver::K - 1)) && (l >= 0 && l <= (Convolver::K - 1))) {
            if ((k >= 0 && k <= (K - 1)) && (l >= 0 && l <= (K - 1))) 
            begin // We're in the Active Section
                if (l == 0) 
                begin // At the left-most column of the register array
                    if (k == 0) begin
                        // Special Case 1: Top Left element of the register array
                        
                        // IMPORTANT DISCUSSION: How do we arrive at the location in the 
                        // shift register array with k and l?
                        // shift_reg index = 1 + (k * N) + l
                        // kernel_2d index = k * K + l
                        mac_unit #(
                            .M(WIDTH),
                            .Q(Q)
                        ) spec_case_1 (
                            .clk(clk),
                            .rst(glb_rst),
                            .clk_en(clk_en),
                            .a(kernel_2d[k * K + l]),
                            .b(input_val),
                            .c(shift_reg[0]),
                            .out(reg_wire_to[1 + (k * N) + l])
                        );
                    end
                    else 
                    begin
                        // Special Case 3: Non-top Left-most element of the register array
                        // Access the right-most register in the previous row.
                        // right-most register of previous row index = 1 + ((k - 1) * N) + (N - 1)
                        mac_unit #(
                            .M(WIDTH),
                            .Q(Q)
                        ) spec_case_3 (
                            .clk(clk),
                            .rst(glb_rst),
                            .clk_en(clk_en),
                            .a(kernel_2d[k * K + l]),
                            .b(input_val),
                            .c(shift_reg[1 + ((k - 1) * N) + (N - 1)]),
                            .out(reg_wire_to[1 + (k * N) + l])
                        );
                    end
                end
                // ((k == (Convolver::K - 1)) && (l == (Convolver::K - 1)))
                else if ((k == (K - 1)) && (l == (K - 1)))
                begin
                    // Special Case 2: Bottom Right element of the register array
                    mac_unit #(
                        .M(WIDTH),
                        .Q(Q)
                    ) spec_case_2 (
                        .clk(clk),
                        .rst(glb_rst),
                        .clk_en(clk_en),
                        .a(kernel_2d[k * K + l]),
                        .b(input_val),
                        .c(shift_reg[(k * N) + l]),
                        .out(reg_wire_to[((K - 1) * N) + K])
                        // Output goes straight to the output of the module via the last element
                        // 1 + ((K - 1) * N) + (K - 1)
                        // (((K - 1) * N) + K)
                        // (((K - 1) * N) + K)
                    );

                    // Note that the validity of the result is disambiguated by the result_valid 
                    // signal, which will be produced by Part 3 (Temporal traversal for output 
                    // element identification)

                end
                else 
                begin
                    // Normal Case: Any other element in the register array
                    mac_unit #(
                        .M(WIDTH),
                        .Q(Q)
                    ) normal_case (
                        .clk(clk),
                        .rst(glb_rst),
                        .clk_en(clk_en),
                        .a(kernel_2d[k * K + l]),
                        .b(input_val),
                        .c(shift_reg[(k * N) + l]),
                        .out(reg_wire_to[1 + (k * N) + l])
                        // Output goes straight to the output of the module via the last element
                        // 1 + ((K - 1) * N) + (K - 1)
                        // (((K - 1) * N) + K)
                        // (((K - 1) * N) + K)
                    );
                end
                always @(posedge clk or posedge glb_rst) begin
                    if (glb_rst) // Global Reset is active, reset all bits
                    begin
                        shift_reg[1 + (k * N) + l] <= 1'b0; // Reset each bit
                    end 
                    
                    else if (clk_en)
                    begin // Clock is enabled, shift the data
                        shift_reg[1 + (k * N) + l] <= reg_wire_to[1 + (k * N) + l]; // Store data
                    end
                end
                
            end
            // ACTIVE SECTION OPERATIONS ENDS HERE

            
            
            // DORMANT SECTION OPERATIONS STARTS HERE
            else 
            begin
                always @(posedge clk or posedge glb_rst) begin
                    if (glb_rst) // Global Reset is active, reset all bits
                    begin
                        if ((1 + (k * N) + l) <= (((K - 1) * N) + K)) begin
                            shift_reg[1 + (k * N) + l] <= 1'b0; // Reset each bit
                        end
                    end 
                    
                    else if (clk_en)
                    begin // Clock is enabled, shift the data
                        if ((1 + (k * N) + l) <= (((K - 1) * N) + K)) begin
                            shift_reg[1 + (k * N) + l] <= shift_reg[(k * N) + l]; // Store data
                        end
                    end
                end
            end
            // DORMANT SECTION OPERATIONS ENDS HERE

        end
        
    end
endgenerate

// PART 2: Spatial traversal for operation definition ENDS HERE

// PART 3: Temporal traversal for output element identification STARTS HERE
// In this part, we have to check if the conv_result at THIS VERY CLOCK is 
// valid or not. This is done by checking if the current input element that 
// is being processed is located at the bottom right corner of the a valid 
// kernel matrix location.

// Firstly, we need a main counter to keep track of the clock cycles.
// The width of this counter should be identical to the total number of
// bit required to index every element of the input matrix.
// This is given by log_2(N * N)
reg [($clog2(N * N) - 1):0] clock_cycle_counter; // 
reg [($clog2(N * N) - 1):0] i;
reg [($clog2(N * N) - 1):0] j;
reg [($clog2(N * N) - 1):0] output_row;

// Now, How do we DERIVE the index of the current element in the input matrix
// from the clock_cycle_counter?
// At reset, both i (row index) and j (column index) are initialized to 0. 
// i increments by 1 after every N clocks, because that's when a whole row of 
// the input matrix is provided.
// j increments by 1 after EVERY clock, because that's when a new element within
// the input matrix is provided. However, j is reset to 0 after every N clocks.
// Because j must be wrapped around after the end of every row.
// j increments by 1 after every clock.

// NOTE: The output can only be produce at the start of the next clock cycle,
// NOT the current one. This is because the output is produced by the MAC unit.
integer r; // Loop variable
integer w; // Loop variable
always @(posedge clk) begin
    if (glb_rst) 
    begin
        // Initialize i and j, the spatial indices of the input matrix derived 
        // from temporal progression.
        i <= 0;
        j <= 0;
        
        // Initialize output signals:
        // conv_result <= {WIDTH{1'b0}}; // Set all WIDTH bits of the output to 0
        result_valid_reg <= 1'b0; // Set the result_valid signal to 0
        conv_end_reg <= 1'b0; // Set the end of convolution signal to 0

        // Initialize the register array to 0
        for (r = 0; r < (1 + ((K - 1) * N) + K); r = r + 1) 
        begin
            shift_reg[r] <= {WIDTH{1'b0}}; // Set all WIDTH bits of row i to 0
        end

    end
    else if (clk_en) 
    begin
        // Notice that we skip the 0th register because it's always 0
        // for (w = 1; w < (1 + ((K - 1) * N) + K); w = w + 1)
        // begin
        //     shift_reg[w] <= reg_wire_to[w];
        // end

        // Indices i and j update rules:
        j <= j + 1;

        if (j == (N - 1)) begin
            // Wrapping imminent for j 
            j <= 0;
            i <= i + 1;
        end

        // conv_end update rules:
        if (
            (i == (N - 1)) &&
            (j == (N - 1))
        ) 
        begin
            conv_end_reg <= 1'b1;
        end
         

        // result_valid update rules:
        if (
            // Check if the current output should be a part of the output
            // The top-left of the current kernel is located at a valid stride
            (((i - (K - 1)) % S) == 0) &&
            (((j - (K - 1)) % S) == 0)
        ) 
        begin
            // The current element is a part of the output
            // $display("We are here.");
            output_row <= $signed((i - (K - 1)) / S);
            if (
                ($signed((i - (K - 1)) / S) >= 0) &&
                ($signed((j - (K - 1)) / S) >= 0)
            ) 
            begin
                result_valid_reg <= 1'b1;
            end
            else 
            begin
                // $display("Are we ever here?");
                result_valid_reg <= 1'b0;
            end
            
            // How do we calculate the target location in the output matrix 
            // where we should put the output in?
            // We actually DO NOT need to worry about it because the output 
            // is directly outputted to the outside scope.
            // POTENTIAL IMPROVEMENT: output the index of the output element
            // within the output matrix as well.
        end
        else 
        begin
            // $display("But are we ever here?");
            result_valid_reg <= 1'b0;
        end

    end
end

// PART 3: Temporal traversal for output element identification ENDS HERE

// initial begin
//     $display("Simulation started");
// end

// initial begin
//     $monitor("Time: %0t | clk: %b | kernel_1d: %d | input_val: %d | i: %d | j: %d | conv_result: %0d | result_valid_reg: %0d | conv_end: %0d", 
//                 $time, clk, kernel_1d, input_val, i, j, conv_result, result_valid_reg, conv_end);
// end

// .a(kernel_2d[k * K + l]),
// .b(input_val),
// .c(shift_reg[(k * N) + l]),
// .out(reg_wire_to[((K - 1) * N) + K])

// Convolver test output
// initial begin
//     $monitor(
//         "Time: %0t | clk: %b | kernel_2d[2]: %d | input_val: %d | shift_reg[2]: %d | shift_reg[3]: %d | reg_wire_to[3]: %d | shift_reg[4]: %d | conv_result: %0d | result_valid_reg: %0d | conv_end: %0d", 
//         $time, clk, kernel_2d[2], input_val, shift_reg[2], shift_reg[3], reg_wire_to[3], shift_reg[4], conv_result, result_valid_reg, conv_end);
// end


endmodule

convolver_tb.v
`timescale 1ns / 1ps


module convolver_tb;
    // Declare testbench signals
    // Inputs:
    reg clk;
    reg clk_en;
    reg reset;

    reg [143:0] kernel;
    reg [15:0] inputs;

    // Outputs:
    wire [15:0] conv_result;
	wire conv_end;
	wire result_valid;

    // Loop variable for iterating through the input matrix:
	integer i;

    // Clock Period
    parameter clk_period = 40;

    

    // Instantiate the design module
    convolution #(
        // .N(9'h004),
        // .K(9'h003),
        // .S(1),
        // .WIDTH(),
        // .Q(),
        // .padding(),
        9'h004,
        9'h003,
        1
    ) 
    design_under_test (
        .clk(clk),
        .clk_en(clk_en),
        .glb_rst(reset),
        .input_val(inputs),
        .kernel_1d(kernel),
        .conv_result(conv_result),
        .result_valid(result_valid),
        .conv_end(conv_end)
    );

    // Clock Signal Generation
    always #(clk_period / 2) clk = ~clk;

    // Initial block to define test stimulus
    initial begin
        // Open a waveform dump file for GTKWave (optional)
        $dumpfile("convolver_tb.vcd");
        $dumpvars(0, convolver_tb);

        // Initialize signals
        clk = 0;
        clk_en = 0;
        reset = 1;   // Apply reset
        kernel = 0;
        inputs = 0;

        // Remove reset and turn on clock enable after 
        // a clock period
        #(clk_period) 
        reset = 0;
        clk_en = 1;

        // Feed, at all clock cycles, the values of the kernel
        kernel = 144'h0008_0007_0006_0005_0004_0003_0002_0001_0000;

        for (i = 0; i < 16; i = i + 1) 
        begin
            
            inputs = i;
            #(clk_period);
        end

        // // Apply test values
        // #10 a = 4'b0011; b = 4'b0101; // Test case 1: a = 3, b = 5
        // #10 a = 4'b1010; b = 4'b0110; // Test case 2: a = 10, b = 6
        // #10 a = 4'b1111; b = 4'b1111; // Test case 3: a = 15, b = 15
        // #10 rst = 1;                 // Apply reset again
        // #10 rst = 0;

        // // End simulation after 50ns
        // #10 
        $finish;
    end

    // Use $monitor to print signal values whenever they change
    initial begin
        $monitor("Time: %0t | clk: %b | inputs: %b | conv_result: %0d | result_valid: %0d | conv_end: %0d", 
                 $time, clk, inputs, conv_result, result_valid, conv_end);
    end
endmodule

convolver_tb.vcd
$date
	Sun Jan 19 01:00:47 2025
$end
$version
	Icarus Verilog
$end
$timescale
	1ps
$end
$scope module convolver_tb $end
$var wire 1 ! result_valid $end
$var wire 16 " conv_result [15:0] $end
$var wire 1 # conv_end $end
$var parameter 32 $ clk_period $end
$var reg 1 % clk $end
$var reg 1 & clk_en $end
$var reg 16 ' inputs [15:0] $end
$var reg 144 ( kernel [143:0] $end
$var reg 1 ) reset $end
$var integer 32 * i [31:0] $end
$scope module design_under_test $end
$var wire 1 % clk $end
$var wire 1 & clk_en $end
$var wire 1 # conv_end $end
$var wire 16 + conv_result [15:0] $end
$var wire 1 ) glb_rst $end
$var wire 16 , input_val [15:0] $end
$var wire 144 - kernel_1d [143:0] $end
$var wire 1 ! result_valid $end
$var parameter 9 . K $end
$var parameter 9 / N $end
$var parameter 32 0 Q $end
$var parameter 32 1 S $end
$var parameter 32 2 WIDTH $end
$var parameter 32 3 padding $end
$var reg 1 4 conv_end_reg $end
$var reg 4 5 i [3:0] $end
$var reg 4 6 j [3:0] $end
$var reg 4 7 output_row [3:0] $end
$var reg 1 8 result_valid_reg $end
$var integer 32 9 r [31:0] $end
$scope begin genblk1[0] $end
$var parameter 2 : n $end
$upscope $end
$scope begin genblk1[1] $end
$var parameter 2 ; n $end
$upscope $end
$scope begin genblk1[2] $end
$var parameter 3 < n $end
$upscope $end
$scope begin genblk1[3] $end
$var parameter 3 = n $end
$upscope $end
$scope begin genblk1[4] $end
$var parameter 4 > n $end
$upscope $end
$scope begin genblk1[5] $end
$var parameter 4 ? n $end
$upscope $end
$scope begin genblk1[6] $end
$var parameter 4 @ n $end
$upscope $end
$scope begin genblk1[7] $end
$var parameter 4 A n $end
$upscope $end
$scope begin genblk1[8] $end
$var parameter 5 B n $end
$upscope $end
$scope begin genblk2[0] $end
$var parameter 2 C k $end
$scope begin genblk1[0] $end
$var parameter 2 D l $end
$scope begin genblk1 $end
$scope begin genblk1 $end
$scope begin genblk1 $end
$scope module spec_case_1 $end
$var wire 16 E a [15:0] $end
$var wire 16 F b [15:0] $end
$var wire 16 G c [15:0] $end
$var wire 1 % clk $end
$var wire 1 & clk_en $end
$var wire 1 ) rst $end
$var wire 16 H out [15:0] $end
$var parameter 32 I M $end
$var parameter 32 J Q $end
$upscope $end
$upscope $end
$upscope $end
$upscope $end
$upscope $end
$scope begin genblk1[1] $end
$var parameter 2 K l $end
$scope begin genblk1 $end
$scope begin genblk1 $end
$scope module normal_case $end
$var wire 16 L a [15:0] $end
$var wire 16 M b [15:0] $end
$var wire 16 N c [15:0] $end
$var wire 1 % clk $end
$var wire 1 & clk_en $end
$var wire 1 ) rst $end
$var wire 16 O out [15:0] $end
$var parameter 32 P M $end
$var parameter 32 Q Q $end
$upscope $end
$upscope $end
$upscope $end
$upscope $end
$scope begin genblk1[2] $end
$var parameter 3 R l $end
$scope begin genblk1 $end
$scope begin genblk1 $end
$scope module normal_case $end
$var wire 16 S a [15:0] $end
$var wire 16 T b [15:0] $end
$var wire 16 U c [15:0] $end
$var wire 1 % clk $end
$var wire 1 & clk_en $end
$var wire 1 ) rst $end
$var wire 16 V out [15:0] $end
$var parameter 32 W M $end
$var parameter 32 X Q $end
$upscope $end
$upscope $end
$upscope $end
$upscope $end
$scope begin genblk1[3] $end
$var parameter 3 Y l $end
$scope begin genblk1 $end
$upscope $end
$upscope $end
$upscope $end
$scope begin genblk2[1] $end
$var parameter 2 Z k $end
$scope begin genblk1[0] $end
$var parameter 2 [ l $end
$scope begin genblk1 $end
$scope begin genblk1 $end
$scope begin genblk1 $end
$scope module spec_case_3 $end
$var wire 16 \ a [15:0] $end
$var wire 16 ] b [15:0] $end
$var wire 16 ^ c [15:0] $end
$var wire 1 % clk $end
$var wire 1 & clk_en $end
$var wire 1 ) rst $end
$var wire 16 _ out [15:0] $end
$var parameter 32 ` M $end
$var parameter 32 a Q $end
$upscope $end
$upscope $end
$upscope $end
$upscope $end
$upscope $end
$scope begin genblk1[1] $end
$var parameter 2 b l $end
$scope begin genblk1 $end
$scope begin genblk1 $end
$scope module normal_case $end
$var wire 16 c a [15:0] $end
$var wire 16 d b [15:0] $end
$var wire 16 e c [15:0] $end
$var wire 1 % clk $end
$var wire 1 & clk_en $end
$var wire 1 ) rst $end
$var wire 16 f out [15:0] $end
$var parameter 32 g M $end
$var parameter 32 h Q $end
$upscope $end
$upscope $end
$upscope $end
$upscope $end
$scope begin genblk1[2] $end
$var parameter 3 i l $end
$scope begin genblk1 $end
$scope begin genblk1 $end
$scope module normal_case $end
$var wire 16 j a [15:0] $end
$var wire 16 k b [15:0] $end
$var wire 16 l c [15:0] $end
$var wire 1 % clk $end
$var wire 1 & clk_en $end
$var wire 1 ) rst $end
$var wire 16 m out [15:0] $end
$var parameter 32 n M $end
$var parameter 32 o Q $end
$upscope $end
$upscope $end
$upscope $end
$upscope $end
$scope begin genblk1[3] $end
$var parameter 3 p l $end
$scope begin genblk1 $end
$upscope $end
$upscope $end
$upscope $end
$scope begin genblk2[2] $end
$var parameter 3 q k $end
$scope begin genblk1[0] $end
$var parameter 2 r l $end
$scope begin genblk1 $end
$scope begin genblk1 $end
$scope begin genblk1 $end
$scope module spec_case_3 $end
$var wire 16 s a [15:0] $end
$var wire 16 t b [15:0] $end
$var wire 16 u c [15:0] $end
$var wire 1 % clk $end
$var wire 1 & clk_en $end
$var wire 1 ) rst $end
$var wire 16 v out [15:0] $end
$var parameter 32 w M $end
$var parameter 32 x Q $end
$upscope $end
$upscope $end
$upscope $end
$upscope $end
$upscope $end
$scope begin genblk1[1] $end
$var parameter 2 y l $end
$scope begin genblk1 $end
$scope begin genblk1 $end
$scope module normal_case $end
$var wire 16 z a [15:0] $end
$var wire 16 { b [15:0] $end
$var wire 16 | c [15:0] $end
$var wire 1 % clk $end
$var wire 1 & clk_en $end
$var wire 1 ) rst $end
$var wire 16 } out [15:0] $end
$var parameter 32 ~ M $end
$var parameter 32 !" Q $end
$upscope $end
$upscope $end
$upscope $end
$upscope $end
$scope begin genblk1[2] $end
$var parameter 3 "" l $end
$scope begin genblk1 $end
$scope begin genblk1 $end
$scope module spec_case_2 $end
$var wire 16 #" a [15:0] $end
$var wire 16 $" b [15:0] $end
$var wire 16 %" c [15:0] $end
$var wire 1 % clk $end
$var wire 1 & clk_en $end
$var wire 1 ) rst $end
$var wire 16 &" out [15:0] $end
$var parameter 32 '" M $end
$var parameter 32 (" Q $end
$upscope $end
$upscope $end
$upscope $end
$upscope $end
$scope begin genblk1[3] $end
$var parameter 3 )" l $end
$scope begin genblk1 $end
$upscope $end
$upscope $end
$upscope $end
$upscope $end
$upscope $end
$enddefinitions $end
$comment Show the parameter values. $end
$dumpall
b11 )"
b1100 ("
b10000 '"
b10 ""
b1100 !"
b10000 ~
b1 y
b1100 x
b10000 w
b0 r
b10 q
b11 p
b1100 o
b10000 n
b10 i
b1100 h
b10000 g
b1 b
b1100 a
b10000 `
b0 [
b1 Z
b11 Y
b1100 X
b10000 W
b10 R
b1100 Q
b10000 P
b1 K
b1100 J
b10000 I
b0 D
b0 C
b1000 B
b111 A
b110 @
b101 ?
b100 >
b11 =
b10 <
b1 ;
b0 :
b1 3
b10000 2
b1 1
b1100 0
b100 /
b11 .
b101000 $
$end
#0
$dumpvars
b0 &"
b0 %"
b0 $"
b0 #"
b0 }
b0 |
b0 {
b0 z
b0 v
b0 u
b0 t
b0 s
b0 m
b0 l
b0 k
b0 j
b0 f
b0 e
b0 d
b0 c
b0 _
b0 ^
b0 ]
b0 \
b0 V
b0 U
b0 T
b0 S
b0 O
b0 N
b0 M
b0 L
bx H
bx G
b0 F
b0 E
bx 9
x8
bx 7
bx 6
bx 5
x4
b0 -
b0 ,
b0 +
bx *
1)
b0 (
b0 '
0&
0%
x#
b0 "
x!
$end
#20000
b0 H
b0 G
0#
04
0!
08
b0 6
b0 5
b1100 9
1%
#40000
b1 L
b10 S
b11 \
b100 c
b101 j
b110 s
b111 z
b1000 #"
0%
b0 *
b100000000000000001110000000000000110000000000000010100000000000001000000000000000011000000000000001000000000000000010000000000000000 (
b100000000000000001110000000000000110000000000000010100000000000001000000000000000011000000000000001000000000000000010000000000000000 -
1&
0)
#60000
b1110 7
b1 6
1%
#80000
0%
b1 O
b10 V
b11 _
b100 f
b101 m
b110 v
b111 }
b1000 &"
b1 '
b1 ,
b1 F
b1 M
b1 T
b1 ]
b1 d
b1 k
b1 t
b1 {
b1 $"
b1 *
#100000
b1000 "
b1000 +
b1111 &"
b111 %"
b1101 }
b110 |
b1001 m
b100 l
b111 f
b11 e
b11 V
b1 U
b10 6
1%
#120000
0%
b10 O
b101 V
b110 _
b1011 f
b1110 m
b1100 v
b10100 }
b10111 &"
b10 '
b10 ,
b10 F
b10 M
b10 T
b10 ]
b10 d
b10 k
b10 t
b10 {
b10 $"
b10 *
#140000
b110 V
b10 U
b1000 _
b10 ^
b1110 f
b110 e
b10101 m
b1011 l
b10001 v
b101 u
b11010 }
b1100 |
b100100 &"
b10100 %"
b10111 "
b10111 +
b11 6
1%
#160000
0%
b11 O
b1000 V
b1011 _
b10010 f
b11010 m
b10111 v
b100001 }
b101100 &"
b11 '
b11 ,
b11 F
b11 M
b11 T
b11 ]
b11 d
b11 k
b11 t
b11 {
b11 $"
b11 *
#180000
b101100 "
b101100 +
b111001 &"
b100001 %"
b101100 }
b10111 |
b100000 v
b1110 u
b100001 m
b10010 l
b10111 f
b1011 e
b1110 _
b101 ^
b1001 V
b11 U
b1 5
b0 6
1%
#200000
0%
b100 O
b1011 V
b10001 _
b11011 f
b100110 m
b100110 v
b110011 }
b1000001 &"
b100 '
b100 ,
b100 F
b100 M
b100 T
b100 ]
b100 d
b100 k
b100 t
b100 {
b100 $"
b100 *
#220000
b1100 V
b100 U
b10100 _
b1000 ^
b100001 f
b10001 e
b101111 m
b11011 l
b110010 v
b11010 u
b1000010 }
b100110 |
b1010011 &"
b110011 %"
b1000001 "
b1000001 +
b1111 7
b1 6
1%
#240000
0%
b101 O
b1110 V
b10111 _
b100101 f
b110100 m
b111000 v
b1001001 }
b1011011 &"
b101 '
b101 ,
b101 F
b101 M
b101 T
b101 ]
b101 d
b101 k
b101 t
b101 {
b101 $"
b101 *
#260000
b1011011 "
b1011011 +
b1110001 &"
b1001001 %"
b1011011 }
b111000 |
b1000100 v
b100110 u
b111110 m
b100101 l
b101011 f
b10111 e
b11010 _
b1011 ^
b1111 V
b101 U
b10 6
1%
#280000
0%
b110 O
b10001 V
b11101 _
b101111 f
b1000011 m
b1001010 v
b1100010 }
b1111001 &"
b110 '
b110 ,
b110 F
b110 M
b110 T
b110 ]
b110 d
b110 k
b110 t
b110 {
b110 $"
b110 *
#300000
b10010 V
b110 U
b100000 _
b1110 ^
b110101 f
b11101 e
b1001101 m
b101111 l
b1011000 v
b110100 u
b1110100 }
b1001010 |
b10010010 &"
b1100010 %"
b1111001 "
b1111001 +
b11 6
1%
#320000
0%
b111 O
b10100 V
b100011 _
b111001 f
b1010010 m
b1011110 v
b1111011 }
b10011010 &"
b111 '
b111 ,
b111 F
b111 M
b111 T
b111 ]
b111 d
b111 k
b111 t
b111 {
b111 $"
b111 *
#340000
b10011010 "
b10011010 +
b10110011 &"
b1111011 %"
b10001111 }
b1011110 |
b1101101 v
b1000011 u
b1011100 m
b111001 l
b111111 f
b100011 e
b100110 _
b10001 ^
b10101 V
b111 U
b10 5
b0 6
1%
#360000
0%
b1000 O
b10111 V
b101001 _
b1000011 f
b1100001 m
b1110011 v
b10010110 }
b10111011 &"
b1000 '
b1000 ,
b1000 F
b1000 M
b1000 T
b1000 ]
b1000 d
b1000 k
b1000 t
b1000 {
b1000 $"
b1000 *
#380000
b11000 V
b1000 U
b101100 _
b10100 ^
b1001001 f
b101001 e
b1101011 m
b1000011 l
b10000010 v
b1010010 u
b10101011 }
b1110011 |
b11010110 &"
b10010110 %"
b10111011 "
b10111011 +
b0 7
b1 6
1%
#400000
0%
b1001 O
b11010 V
b101111 _
b1001101 f
b1110000 m
b10001000 v
b10110010 }
b11011110 &"
b1001 '
b1001 ,
b1001 F
b1001 M
b1001 T
b1001 ]
b1001 d
b1001 k
b1001 t
b1001 {
b1001 $"
b1001 *
#420000
b11011110 "
b11011110 +
b11111010 &"
b10110010 %"
b11000111 }
b10001000 |
b10010111 v
b1100001 u
b1111010 m
b1001101 l
b1010011 f
b101111 e
b110010 _
b10111 ^
b11011 V
b1001 U
b10 6
1%
#440000
0%
b1010 O
b11101 V
b110101 _
b1010111 f
b1111111 m
b10011101 v
b11001110 }
b100000010 &"
b1010 '
b1010 ,
b1010 F
b1010 M
b1010 T
b1010 ]
b1010 d
b1010 k
b1010 t
b1010 {
b1010 $"
b1010 *
#460000
b11110 V
b1010 U
b111000 _
b11010 ^
b1011101 f
b110101 e
b10001001 m
b1010111 l
b10101100 v
b1110000 u
b11100011 }
b10011101 |
b100011110 &"
b11001110 %"
b100000010 "
b100000010 +
1!
18
b11 6
1%
#480000
0%
b1011 O
b100000 V
b111011 _
b1100001 f
b10001110 m
b10110010 v
b11101010 }
b100100110 &"
b1011 '
b1011 ,
b1011 F
b1011 M
b1011 T
b1011 ]
b1011 d
b1011 k
b1011 t
b1011 {
b1011 $"
b1011 *
#500000
b100100110 "
b100100110 +
b101000010 &"
b11101010 %"
b11111111 }
b10110010 |
b11000001 v
b1111111 u
b10011000 m
b1100001 l
b1100111 f
b111011 e
b111110 _
b11101 ^
b100001 V
b1011 U
b11 5
b0 6
1%
#520000
0%
b1100 O
b100011 V
b1000001 _
b1101011 f
b10011101 m
b11000111 v
b100000110 }
b101001010 &"
b1100 '
b1100 ,
b1100 F
b1100 M
b1100 T
b1100 ]
b1100 d
b1100 k
b1100 t
b1100 {
b1100 $"
b1100 *
#540000
b100100 V
b1100 U
b1000100 _
b100000 ^
b1110001 f
b1000001 e
b10100111 m
b1101011 l
b11010110 v
b10001110 u
b100011011 }
b11000111 |
b101100110 &"
b100000110 %"
b101001010 "
b101001010 +
0!
08
b1 7
b1 6
1%
#560000
0%
b1101 O
b100110 V
b1000111 _
b1110101 f
b10101100 m
b11011100 v
b100100010 }
b101101110 &"
b1101 '
b1101 ,
b1101 F
b1101 M
b1101 T
b1101 ]
b1101 d
b1101 k
b1101 t
b1101 {
b1101 $"
b1101 *
#580000
b101101110 "
b101101110 +
b110001010 &"
b100100010 %"
b100110111 }
b11011100 |
b11101011 v
b10011101 u
b10110110 m
b1110101 l
b1111011 f
b1000111 e
b1001010 _
b100011 ^
b100111 V
b1101 U
b10 6
1%
#600000
0%
b1110 O
b101001 V
b1001101 _
b1111111 f
b10111011 m
b11110001 v
b100111110 }
b110010010 &"
b1110 '
b1110 ,
b1110 F
b1110 M
b1110 T
b1110 ]
b1110 d
b1110 k
b1110 t
b1110 {
b1110 $"
b1110 *
